coolprop_oop/__init__.py
coolprop_oop/coolprop_oop.py
tests/__init__.py
tests/test_coolprop_oop.py
coolprop_oop-2.0.0.dist-info/LICENSE
coolprop_oop-2.0.0.dist-info/METADATA
coolprop_oop-2.0.0.dist-info/WHEEL
coolprop_oop-2.0.0.dist-info/top_level.txt
coolprop_oop-2.0.0.dist-info/RECORD
