Metadata-Version: 2.2
Name: coolprop-oop
Version: 2.0.0
Summary: A Pythonic object-oriented wrapper for CoolProp with property validation, state management, and all thermodynamic properties settable
Home-page: https://github.com/ryancoxrbc/coolprop_oop
Author: Ryan Cox
Author-email: ryanbradleycox@gmail.com
Classifier: Programming Language :: Python :: 3
Classifier: License :: OSI Approved :: MIT License
Classifier: Operating System :: OS Independent
Classifier: Topic :: Scientific/Engineering :: Physics
Classifier: Topic :: Scientific/Engineering :: Chemistry
Classifier: Intended Audience :: Science/Research
Classifier: Intended Audience :: Education
Classifier: Development Status :: 5 - Production/Stable
Requires-Python: >=3.8
License-File: LICENSE
Requires-Dist: CoolProp>=6.7.0
Dynamic: author
Dynamic: author-email
Dynamic: classifier
Dynamic: description
Dynamic: description-content-type
Dynamic: home-page
Dynamic: requires-dist
Dynamic: requires-python
Dynamic: summary
